dfu/__about__.py
dfu/__init__.py
dfu/__main__.py
dfu/cli.py
dfu/config.py
dfu/api/__init__.py
dfu/api/entrypoint.py
dfu/api/playground.py
dfu/api/plugin.py
dfu/api/state.py
dfu/api/store.py
dfu/commands/__init__.py
dfu/commands/apply.py
dfu/commands/create_config.py
dfu/commands/create_package.py
dfu/commands/create_snapshot.py
dfu/commands/diff.py
dfu/commands/load_config.py
dfu/commands/load_store.py
dfu/commands/ls_files.py
dfu/commands/shell.py
dfu/helpers/json_serializable.py
dfu/helpers/normalize_snapshot_index.py
dfu/helpers/subshell.py
dfu/package/package_config.py
dfu/plugins/autosave.py
dfu/plugins/pacman.py
dfu/revision/git.py
dfu/snapshots/btrfs.py
dfu/snapshots/changes.py
dfu/snapshots/proot.py
dfu/snapshots/snapper.py
dfu/snapshots/snapper_diff.py
dfu/snapshots/sort_snapper_configs.py
dfu-0.0.5.dist-info/METADATA
dfu-0.0.5.dist-info/WHEEL
dfu-0.0.5.dist-info/entry_points.txt
dfu-0.0.5.dist-info/licenses/LICENSE
dfu-0.0.5.dist-info/RECORD
